pyqt_number_lineedit/__init__.py
pyqt_number_lineedit/numberLineEdit.py
pyqt_number_lineedit-0.0.1.dist-info/LICENSE
pyqt_number_lineedit-0.0.1.dist-info/METADATA
pyqt_number_lineedit-0.0.1.dist-info/WHEEL
pyqt_number_lineedit-0.0.1.dist-info/top_level.txt
pyqt_number_lineedit-0.0.1.dist-info/RECORD
