Metadata-Version: 2.1
Name: pyqt-number-lineedit
Version: 0.0.1
Summary: QLineEdit which allows only numeric input
Home-page: https://github.com/yjg30737/pyqt-number-lineedit.git
Author: Jung Gyu Yoon
Author-email: yjg30737@gmail.com
License: MIT
Platform: UNKNOWN
License-File: LICENSE
Requires-Dist: PyQt5 (>=5.8)
